LICENSE
README.md
setup.py
django_encrypted_searchable_fields.egg-info/PKG-INFO
django_encrypted_searchable_fields.egg-info/SOURCES.txt
django_encrypted_searchable_fields.egg-info/dependency_links.txt
django_encrypted_searchable_fields.egg-info/requires.txt
django_encrypted_searchable_fields.egg-info/top_level.txt
encrypted_fields/__init__.py
encrypted_fields/fields.py