Metadata-Version: 2.1
Name: django-encrypted-searchable-fields
Version: 0.2.0
Summary: A fork of django-searchable-encrypted-fields with a bug fix.
Home-page: https://github.com/ucoran-saas/django-encrypted-searchable-fields/
Author: Guy Willett
Author-email: <guy@chamsoft.co>
Maintainer: Kenny Lajara
License: MIT
Platform: UNKNOWN
Classifier: License :: OSI Approved :: MIT License
Classifier: Operating System :: OS Independent
Classifier: Programming Language :: Python :: 3.8
Classifier: Programming Language :: Python :: 3.9
Classifier: Framework :: Django
Classifier: Framework :: Django :: 3.2
Classifier: Framework :: Django :: 4.0
Classifier: Framework :: Django :: 4.1
License-File: LICENSE
